eyepop/__init__.py
eyepop/_version.py
eyepop/client_event.fbs
eyepop/client_session.py
eyepop/endpoint.py
eyepop/exceptions.py
eyepop/eyepopsdk.py
eyepop/jobs.py
eyepop/logging.py
eyepop/metrics.py
eyepop/periodic.py
eyepop/py.typed
eyepop/request_tracer.py
eyepop/settings.py
eyepop/syncify.py
eyepop/visualize.py
eyepop/compute/__init__.py
eyepop/compute/api.py
eyepop/compute/context.py
eyepop/compute/responses.py
eyepop/compute/status.py
eyepop/data/__init__.py
eyepop/data/data_endpoint.py
eyepop/data/data_jobs.py
eyepop/data/data_normalize.py
eyepop/data/data_syncify.py
eyepop/data/data_top_k.py
eyepop/data/data_types.py
eyepop/data/arrow/__init__.py
eyepop/data/arrow/schema.py
eyepop/data/arrow/schema_0_0.py
eyepop/data/arrow/schema_1_0.py
eyepop/data/arrow/schema_1_1.py
eyepop/data/arrow/schema_1_2.py
eyepop/data/arrow/schema_1_3.py
eyepop/data/arrow/schema_1_4.py
eyepop/data/arrow/schema_1_5.py
eyepop/data/arrow/schema_1_6.py
eyepop/data/arrow/schema_1_7.py
eyepop/data/arrow/schema_version_conversion.py
eyepop/data/arrow/streaming.py
eyepop/data/arrow/eyepop/__init__.py
eyepop/data/arrow/eyepop/annotations.py
eyepop/data/arrow/eyepop/assets.py
eyepop/data/arrow/eyepop/predictions.py
eyepop/data/arrow/pandas/__init__.py
eyepop/data/arrow/pandas/assets.py
eyepop/events/ClientType.py
eyepop/events/Event.py
eyepop/events/Method.py
eyepop/events/Record.py
eyepop/events/Result.py
eyepop/events/__init__.py
eyepop/worker/__init__.py
eyepop/worker/load_balancer.py
eyepop/worker/worker_client_session.py
eyepop/worker/worker_endpoint.py
eyepop/worker/worker_jobs.py
eyepop/worker/worker_syncify.py
eyepop/worker/worker_types.py
eyepop-3.9.3.dist-info/licenses/LICENSE
eyepop-3.9.3.dist-info/METADATA
eyepop-3.9.3.dist-info/WHEEL
eyepop-3.9.3.dist-info/top_level.txt
eyepop-3.9.3.dist-info/RECORD
