Metadata-Version: 2.4
Name: eyepop
Version: 3.9.3
Summary: EyePop.ai Python SDK
Author-email: "EyePop.ai" <support@eyepop.ai>
License-Expression: MIT
Project-URL: Homepage, https://github.com/eyepop-ai/eyepop-sdk-python
Project-URL: Repository, https://github.com/eyepop-ai/eyepop-sdk-python
Keywords: EyePop,AI,ML,CV
Requires-Python: >=3.12
License-File: LICENSE
Requires-Dist: aiohttp<4.0.0,>=3.9.0
Requires-Dist: cryptography<47.0.0,>=42.0.0
Requires-Dist: deprecated<2.0.0,>=1.2.0
Requires-Dist: flatbuffers<26.0.0,>=24.0.0
Requires-Dist: matplotlib<4.0.0,>=3.8.0
Requires-Dist: pandas<3.0.0,>=2.0.0
Requires-Dist: pyarrow<22.0.0,>=17.0.0
Requires-Dist: pydantic<3.0.0,>=2.0.0
Requires-Dist: pydantic-settings<3.0.0,>=2.0.0
Requires-Dist: websockets<16.0.0,>=13.0.0
Provides-Extra: test
Requires-Dist: aioresponses>=0.7.8; extra == "test"
Requires-Dist: pytest; extra == "test"
Requires-Dist: pytest-asyncio; extra == "test"
Requires-Dist: pytest-cov; extra == "test"
Requires-Dist: codecov; extra == "test"
Requires-Dist: pre-commit; extra == "test"
Requires-Dist: parameterized>=0.9.0; extra == "test"
Provides-Extra: doc
Requires-Dist: mkdocs; extra == "doc"
Requires-Dist: mkdocstrings; extra == "doc"
Requires-Dist: mkdocstrings[python]; extra == "doc"
Requires-Dist: mkdocs-material; extra == "doc"
Requires-Dist: Pygments; extra == "doc"
Provides-Extra: example
Requires-Dist: pyqt5; extra == "example"
Requires-Dist: webui2; extra == "example"
Requires-Dist: pybars3; extra == "example"
Requires-Dist: python-dotenv; extra == "example"
Requires-Dist: aiofiles==25.1.0; extra == "example"
Requires-Dist: auth0-python>=4.13.0; extra == "example"
Provides-Extra: dev
Requires-Dist: build<2.0.0,>=1.0.0; extra == "dev"
Requires-Dist: mypy<2.0.0,>=1.8.0; extra == "dev"
Requires-Dist: ruff<1.0.0,>=0.6.0; extra == "dev"
Requires-Dist: types-aiofiles; extra == "dev"
Requires-Dist: types-Pillow; extra == "dev"
Provides-Extra: all
Requires-Dist: eyepop[dev,doc,example,test]; extra == "all"
Dynamic: license-file
